exogym/__init__.py
exogym-0.0.0a0.dist-info/METADATA
exogym-0.0.0a0.dist-info/WHEEL
exogym-0.0.0a0.dist-info/top_level.txt
exogym-0.0.0a0.dist-info/RECORD
