Metadata-Version: 2.4
Name: exogym
Version: 0.0.0a0
Summary: Simulate distributed training on local devices
Author-email: Matt Beton <matthew.beton@gmail.com>
License: MIT
Classifier: Programming Language :: Python :: 3
Requires-Python: >=3.10
